devops_toolkit/__init__.py
devops_toolkit/cli.py
devops_toolkit/docker_optimizer/__init__.py
devops_toolkit/docker_optimizer/optimizer.py
devops_toolkit/k8s_linter/__init__.py
devops_toolkit/k8s_linter/linter.py
devops_file_toolkit-0.1.0.dist-info/METADATA
devops_file_toolkit-0.1.0.dist-info/WHEEL
devops_file_toolkit-0.1.0.dist-info/entry_points.txt
devops_file_toolkit-0.1.0.dist-info/top_level.txt
devops_file_toolkit-0.1.0.dist-info/RECORD
