Metadata-Version: 2.4
Name: devops-file-toolkit
Version: 0.1.0
Summary: A toolkit for Dockerfile optimization and Kubernetes YAML linting
Home-page: https://github.com/JaguarsCodehub/devops-toolkit
Author: Jyotindra KT
Author-email: jyotindrakt21@gmail.com
Classifier: Programming Language :: Python :: 3
Classifier: License :: OSI Approved :: MIT License
Classifier: Operating System :: OS Independent
Requires-Python: >=3.6
Requires-Dist: PyYAML
Requires-Dist: argparse
Dynamic: author
Dynamic: author-email
Dynamic: classifier
Dynamic: description
Dynamic: description-content-type
Dynamic: home-page
Dynamic: requires-dist
Dynamic: requires-python
Dynamic: summary
